fedoidc/__init__.py
fedoidc/bundle.py
fedoidc/client.py
fedoidc/entity.py
fedoidc/file_system.py
fedoidc/operator.py
fedoidc/provider.py
fedoidc/rp_handler.py
fedoidc/signing_service.py
fedoidc/test_utils.py
fedoidc-0.3.0.dist-info/DESCRIPTION.rst
fedoidc-0.3.0.dist-info/METADATA
fedoidc-0.3.0.dist-info/RECORD
fedoidc-0.3.0.dist-info/WHEEL
fedoidc-0.3.0.dist-info/metadata.json
fedoidc-0.3.0.dist-info/top_level.txt
